minihydra/README.md
minihydra/__init__.py
minihydra_leviathan-1.0.1.dist-info/METADATA
minihydra_leviathan-1.0.1.dist-info/WHEEL
minihydra_leviathan-1.0.1.dist-info/top_level.txt
minihydra_leviathan-1.0.1.dist-info/RECORD
