Metadata-Version: 2.1
Name: minihydra-leviathan
Version: 1.0.1
Summary: A lightweight sys-arg manager.
Home-page: https://github.com/Cave-Dwellers-Tree-People/minihydra
Author: Sam Lerman
Author-email: cave.dwellers.tree.people@gmail.com
Project-URL: Bug Tracker, https://github.com/Cave-Dwellers-Tree-People/minihydra/issues
Keywords: sys args,hyperparams,command line,artificial intelligence,machine learning,deep learning,reinforcement learning,image classification
Classifier: Programming Language :: Python
Classifier: License :: OSI Approved :: MIT License
Classifier: Operating System :: OS Independent
Requires-Python: >=3.10.8
Requires-Dist: PyYAML (>=6.0)
